.gitignore
MANIFEST.in
README.rst
bootstrap.py
buildout.cfg
setup.py
collective/__init__.py
collective.portlet.lingualinks.egg-info/PKG-INFO
collective.portlet.lingualinks.egg-info/SOURCES.txt
collective.portlet.lingualinks.egg-info/dependency_links.txt
collective.portlet.lingualinks.egg-info/entry_points.txt
collective.portlet.lingualinks.egg-info/namespace_packages.txt
collective.portlet.lingualinks.egg-info/not-zip-safe
collective.portlet.lingualinks.egg-info/requires.txt
collective.portlet.lingualinks.egg-info/top_level.txt
collective/portlet/__init__.py
collective/portlet/lingualinks/__init__.py
collective/portlet/lingualinks/configure.zcml
collective/portlet/lingualinks/controlpanel.py
collective/portlet/lingualinks/interfaces.py
collective/portlet/lingualinks/msgids.py
collective/portlet/lingualinks/portlet.pt
collective/portlet/lingualinks/portlet.py
collective/portlet/lingualinks/rebuild_i18n.sh
collective/portlet/lingualinks/testing.py
collective/portlet/lingualinks/locales/collective.portlet.lingualinks.pot
collective/portlet/lingualinks/locales/fr/LC_MESSAGES/collective.portlet.lingualinks.po
collective/portlet/lingualinks/profiles/default/controlpanel.xml
collective/portlet/lingualinks/profiles/default/metadata.xml
collective/portlet/lingualinks/profiles/default/portlets.xml
collective/portlet/lingualinks/profiles/default/registry.xml
collective/portlet/lingualinks/tests/__init__.py
collective/portlet/lingualinks/tests/base.py
collective/portlet/lingualinks/tests/test_portlet.py
collective/portlet/lingualinks/tests/test_setup.py
collective/portlet/lingualinks/tests/utils.py
collective/portlet/lingualinks/upgrades/__init__.py
collective/portlet/lingualinks/upgrades/configure.zcml
collective/portlet/lingualinks/upgrades/v1000_to_1001.py
docs/HISTORY.txt