Metadata-Version: 1.0
Name: collective.portlet.lingualinks
Version: 1.1
Summary: A portlet to provide links to translated content
Home-page: https://github.com/collective/collective/collective.portlet.lingualinks
Author: JeanMichel FRANCOIS
Author-email: toutpt@gmail.com
License: GPL
Keywords: plone multilingual linguaplone portlet
Platform: UNKNOWN
Classifier: Programming Language :: Python
Classifier: Framework :: Plone
Classifier: Framework :: Plone :: 4.0
Classifier: Framework :: Plone :: 4.1
Classifier: Framework :: Plone :: 4.2
